{
  "version": "1.0",
  "timestamp": "2026-05-22T21:20:51.085Z",
  "source": "auto-postool",
  "partial": false,
  "phase": null,
  "phase_name": null,
  "phase_dir": null,
  "plan": null,
  "task": null,
  "total_tasks": null,
  "status": "auto-checkpoint",
  "completed_tasks": [],
  "remaining_tasks": [],
  "blockers": [],
  "human_actions_pending": [],
  "decisions": [],
  "uncommitted_files": [
    {
      "status": "M",
      "path": ".memory/scripts/flush.log"
    },
    {
      "status": "M",
      "path": ".memory/scripts/last-flush.json"
    },
    {
      "status": "M",
      "path": ".planning/HANDOFF.json"
    },
    {
      "status": "M",
      "path": "docs/ARCHITECTURE.md"
    },
    {
      "status": "??",
      "path": ".memory/daily/2026-05-23.md"
    },
    {
      "status": "??",
      "path": ".memory/knowledge/concepts/feed-map-filter-symmetry.md"
    },
    {
      "status": "??",
      "path": ".memory/knowledge/concepts/filter-presets-favorites.md"
    },
    {
      "status": "??",
      "path": ".memory/knowledge/concepts/unnest-multi-column-alias-no-types.md"
    }
  ],
  "next_action": null,
  "context_notes": "Recent commits:\n9689020 DOCS: актуализировать web.md и README под текущий UI\n10525c2 CHORE: sync dev с main (af13351)\naf13351 FIX: имя актора в событиях + кеш-баг создания поездки\nb2ae4f1 REFACTOR: лента+карта симметрия + пресеты фильтров\n084cbf2 FEAT: пресеты фильтров вместо избранных водителей"
}
